iart/__init__.py
iart/main.py
iart/modules/RowCreator.py
iart/modules/__init__.py
iart/modules/csvExporter.py
iart/modules/safetypy.py
iart-1.0.1.dist-info/entry_points.txt
iart-1.0.1.dist-info/LICENSE
iart-1.0.1.dist-info/WHEEL
iart-1.0.1.dist-info/METADATA
iart-1.0.1.dist-info/RECORD
